{"genre":"TECHNO \/ HOUSE","library_folder_count":"2","persistent_id":"E658F867FC1F3525","sample_rate":"44100","track_id":"4277","total_time":"152120","name":"The House Of The Followers","date_added":"2015-04-29T05:44:37Z","file_folder_count":"2","artist":"Vatican Shadow","track_type":"File","size":"17523127","year":"2012","track_number":"2","kind":"Apple Lossless audio file","bit_rate":"1411","date_modified":"2015-04-29T05:33:31Z","sort_name":"House Of The Followers","album":"Ghosts Of Chechnya","location":"file:\/\/\/Users\/l1x\/Music\/Vatican_Shadow-Ghosts_Of_Chechnya\/2-The_House_Of_The_Followers.m4a"}