{"genre":"Other","library_folder_count":"2","persistent_id":"BDDF924521B7DB72","sample_rate":"44100","track_id":"3529","total_time":"110173","name":"Falling Awake","date_added":"2015-04-29T05:44:37Z","file_folder_count":"2","artist":"Shpongle","track_type":"File","size":"10006651","year":"2005","track_number":"20","kind":"Apple Lossless audio file","bit_rate":"1411","date_modified":"2015-04-29T05:22:56Z","album":"Nothing Lasts... But Nothing Is Lost","location":"file:\/\/\/Users\/l1x\/Music\/Shpongle_-_Nothing_Lasts..._But_Nothing_Is_Lost\/20_-_Falling_Awake.m4a"}