{"genre":"Synthpop","library_folder_count":"2","disc_number":"2","persistent_id":"3581D29A53A97E8C","sample_rate":"44100","track_id":"1647","total_time":"346133","name":"Home","date_added":"2015-04-29T05:44:37Z","file_folder_count":"3","artist":"Depeche Mode","track_type":"File","size":"41859065","year":"1998","track_number":"7","kind":"Apple Lossless audio file","bit_rate":"1411","date_modified":"2015-05-01T05:45:08Z","album":"The Singles 86>98","location":"file:\/\/\/Users\/l1x\/Music\/Depeche_Mode_-_The_Singles_86-98\/CD2\/07_-_Home.m4a","album_artist":"Depeche Mode","sort_album":"Singles 86>98"}