{"library_folder_count":"2","persistent_id":"E2FCBBF60306EF82","sample_rate":"44100","track_id":"5415","total_time":"389213","artwork_count":"1","name":"Headroom (Digital Bonus - original released on label compilation only)","date_added":"2015-05-01T07:28:36Z","comments":"Visit http:\/\/infracom.bandcamp.com","file_folder_count":"2","artist":"Phoneheads","track_type":"File","size":"48212125","year":"1999","track_number":"11","kind":"Apple Lossless audio file","bit_rate":"1411","date_modified":"2015-05-01T07:30:38Z","album":"Peak Position","location":"file:\/\/\/Users\/l1x\/Music\/Phoneheads_-_Peak_Position\/Phoneheads_-_Peak_Position_-_11_Headroom_(Digital_Bonus_-_original_released_on_label_compilation_only).m4a","album_artist":"Phoneheads"}