{"genre":"Hip-Hop","library_folder_count":"2","disc_number":"1","persistent_id":"974D57ED3CA5A452","sample_rate":"44100","track_id":"2409","total_time":"31666","name":"6-40","date_added":"2015-04-29T05:44:37Z","file_folder_count":"2","artist":"Karriem Riggins","track_type":"File","size":"2721773","year":"2012","track_number":"28","composer":"Karriem Riggins","kind":"Apple Lossless audio file","bit_rate":"1411","date_modified":"2015-04-29T05:07:01Z","album":"Alone Together","location":"file:\/\/\/Users\/l1x\/Music\/Karriem_Riggins_-_Alone_Together\/28_6-40.m4a"}