{"genre":"Electronic","library_folder_count":"2","persistent_id":"19092F8E8625C53A","sample_rate":"44100","track_id":"4159","total_time":"329253","artwork_count":"1","name":"Zat","date_added":"2015-04-29T05:44:37Z","file_folder_count":"2","artist":"Orange Kush","track_type":"File","size":"38402194","year":"2000","track_number":"10","kind":"Apple Lossless audio file","bit_rate":"1411","date_modified":"2015-05-01T06:06:17Z","album":"Urban Funk Breaks","location":"file:\/\/\/Users\/l1x\/Music\/Urban_Funk_Breaks\/10_-_Orange_Kush_-_Zat_-_Orange_Kush_-_Zat.m4a","compilation":null}