{"genre":"Dub","library_folder_count":"2","persistent_id":"A0C39ABA3670B12B","sample_rate":"44100","track_id":"3027","total_time":"427466","name":"Spannered in Pilton","date_added":"2015-04-29T05:44:37Z","file_folder_count":"2","artist":"Ott","track_type":"File","size":"50179960","year":"2003","track_number":"8","kind":"Apple Lossless audio file","bit_rate":"1411","date_modified":"2015-04-29T05:15:41Z","album":"Blumenkraft","location":"file:\/\/\/Users\/l1x\/Music\/Ott_-_Blumenkraft\/08_-_Ott_-_Spannered_in_Pilton.m4a"}