{"genre":"Downtempo","library_folder_count":"2","persistent_id":"83A871382E4D1DC8","sample_rate":"44100","track_id":"1045","total_time":"248933","name":"Shadowtricks","date_added":"2015-04-29T05:44:37Z","file_folder_count":"2","artist":"Bonobo","track_type":"File","size":"21708332","year":"2001","track_number":"7","kind":"Apple Lossless audio file","bit_rate":"1411","date_modified":"2015-04-29T04:47:03Z","album":"Animal Magic","location":"file:\/\/\/Users\/l1x\/Music\/Bonobo_-_Animal_Magic\/07_-_Shadowtricks.m4a"}