{"genre":"Disco","library_folder_count":"2","persistent_id":"952CBE5EBFC70134","sample_rate":"44100","track_id":"4673","total_time":"429949","name":"Spacer Woman","date_added":"2015-04-29T05:47:14Z","file_folder_count":"2","artist":"Charlie","track_type":"File","size":"12150656","year":"2005","track_number":"1","kind":"MPEG audio file","bit_rate":"226","date_modified":"2015-05-04T02:07:04Z","album":"Spacer Woman","location":"file:\/\/\/Users\/l1x\/Music\/Charlie_-_Spacer_Woman\/Charlie_-_Spacer_Woman.mp3"}