{"genre":"Reggae","library_folder_count":"2","persistent_id":"22A89B6D55091F7A","sample_rate":"44100","track_id":"5011","total_time":"179591","name":"You Don't Have To Know Me","date_added":"2015-04-29T05:47:14Z","file_folder_count":"2","artist":"Milton Henry","track_type":"File","size":"7185720","year":"1985","track_number":"9","kind":"MPEG audio file","bit_rate":"320","date_modified":"2015-04-29T05:46:54Z","album":"Who Do You Think I Am?","location":"file:\/\/\/Users\/l1x\/Music\/Milton_Henry_-_Who_Do_You_Think_I_Am\/09_-_You_Don't_Have_To_Know_Me.mp3"}