{"genre":"Electronica","library_folder_count":"2","disc_number":"1","persistent_id":"8DF8968A48428EB1","sample_rate":"44100","track_id":"4825","total_time":"401449","artwork_count":"1","name":"Building Steam With A Grain Of Salt","date_added":"2015-04-29T05:47:14Z","comments":" ID3G:  17 YEAR: 1996","file_folder_count":"3","artist":"DJ Shadow","track_type":"File","size":"10887198","year":"1996","disc_count":"1","track_number":"2","composer":"Jeremy Storch","kind":"MPEG audio file","bit_rate":"216","date_modified":"2015-04-29T05:46:51Z","album":"Endtroducing...","location":"file:\/\/\/Users\/l1x\/Music\/DJ_Shadow_-_Endtroducing\/CD_1\/02_-_DJ_Shadow_-_Building_Steam_With_A_Grain_Of_Salt.mp3","album_artist":"DJ Shadow"}