{"genre":null,"library_folder_count":"2","persistent_id":"8C8F74DC09A55727","sample_rate":"44100","track_id":"5201","total_time":"178311","artwork_count":"1","name":"Calling You","date_added":"2015-04-29T05:47:14Z","sort_album_artist":"Cas!o Samples","comments":" YEAR: 2001","file_folder_count":"2","artist":"The Cas!o Samples","track_type":"File","size":"4335862","year":"2001","track_number":"11","kind":"MPEG audio file","bit_rate":"192","date_modified":"2015-05-03T23:22:11Z","sort_artist":"Cas!o Samples","album":"Cutting Age","location":"file:\/\/\/Users\/l1x\/Music\/The_Cas!o_Samples_-_Cutting_Age\/11_-_Calling_You.mp3","album_artist":"The Cas!o Samples"}