{"genre":"Electronic","library_folder_count":"2","persistent_id":"C819594B123445C8","sample_rate":"44100","track_id":"817","total_time":"33040","name":"Interlude - London Massive","date_added":"2015-04-29T04:34:57Z","file_folder_count":"2","artist":"Aphrodite","track_type":"File","size":"3636104","year":"2002","track_number":"16","kind":"Apple Lossless audio file","bit_rate":"1411","date_modified":"2015-05-03T23:19:57Z","album":"Aftershock","location":"file:\/\/\/Users\/l1x\/Music\/Aphrodite_-_Aftershock_flac\/16_-_Interlude_-_London_Massive.m4a","album_artist":"Aphrodite"}